auth_utils/__init__.py
auth_utils/exceptions.py
auth_utils/middlewares.py
auth_utils/schemas.py
authutilsvpetrov-0.1.7.dist-info/METADATA
authutilsvpetrov-0.1.7.dist-info/WHEEL
authutilsvpetrov-0.1.7.dist-info/top_level.txt
authutilsvpetrov-0.1.7.dist-info/RECORD
