Metadata-Version: 2.1
Name: authutilsvpetrov
Version: 0.1.7
Summary: description
Home-page: 
Author: Vladimir Petrov
Author-email: 
Classifier: Programming Language :: Python :: 3
Classifier: License :: OSI Approved :: MIT License
Classifier: Operating System :: OS Independent
Requires-Python: >=3.6
Requires-Dist: fastapi
Requires-Dist: pydantic
Requires-Dist: typing
Requires-Dist: userutilsvpetrov
